Lab-2/circuit2.v
module simple_circuit(Y, A, B, C);
input A,B,C;
output Y;
wire w1, w2, w3;
and g1(w1, B, C);
or g2(w2, A, w1);
and g3(w3, A, B);
or g4(Y, w2, w3);
endmodule

Lab-2/circuit1_tb.v
module tb_simple_circuit;

reg A,B,C;
wire Y;

simple_circuit M1(.A(A), .B(B), .C(C), .Y(Y));

initial

begin

A=1'b0 ; B=1'b0 ; C=1'b0;
#20
A=1'b0 ; B=1'b0 ; C=1'b1;
#20
A=1'b0 ; B=1'b1 ; C=1'b0;
#20
A=1'b0 ; B=1'b1 ; C=1'b1;
#20
A=1'b1 ; B=1'b0 ; C=1'b0;
#20
A=1'b1 ; B=1'b0 ; C=1'b1;
#20
A=1'b1 ; B=1'b1 ; C=1'b0;
#20
A=1'b1 ; B=1'b1 ; C=1'b1;

end


initial
begin
$monitor($time, "A=%b, B=%b, C=%b,Y=%b", A,B,C,Y);
end
initial
begin
$dumpfile ("circuit1.vcd");
 $dumpvars (0, tb_simple_circuit);
end
endmodule

Lab-2/circuit2.vcd
$date
	Tue Aug 16 19:34:15 2022
$end
$version
	Icarus Verilog
$end
$timescale
	1s
$end
$scope module tb_simple_circuit $end
$var wire 1 ! Y $end
$var reg 1 " A $end
$var reg 1 # B $end
$var reg 1 $ C $end
$scope module M1 $end
$var wire 1 % A $end
$var wire 1 & B $end
$var wire 1 ' C $end
$var wire 1 ! Y $end
$var wire 1 ( w1 $end
$var wire 1 ) w2 $end
$var wire 1 * w3 $end
$upscope $end
$upscope $end
$enddefinitions $end
#0
$dumpvars
0*
0)
0(
0'
0&
0%
0$
0#
0"
0!
$end
#20
1$
1'
#40
0$
0'
1#
1&
#60
1!
1)
1(
1$
1'
#80
0(
0$
0'
0#
0&
1"
1%
#100
1$
1'
#120
1*
0$
0'
1#
1&
#140
1(
1$
1'
