Lab-2/circuit1.v
module simple_circuit(Y, A, B, C);
input A,B,C;
output Y;
wire w1, w2, w3;
and g1(w1, B, C);
or g2(Y, A, w1);
endmodule

Lab-2/circuit2_tb.v
module tb_simple_circuit;

reg A,B,C;
wire Y;

simple_circuit M1(A, B, C, Y);

initial

begin

A=1'b0 ; B=1'b0 ; C=1'b0;
#20
A=1'b0 ; B=1'b0 ; C=1'b1;
#20
A=1'b0 ; B=1'b1 ; C=1'b0;
#20
A=1'b0 ; B=1'b1 ; C=1'b1;
#20
A=1'b1 ; B=1'b0 ; C=1'b0;
#20
A=1'b1 ; B=1'b0 ; C=1'b1;
#20
A=1'b1 ; B=1'b1 ; C=1'b0;
#20
A=1'b1 ; B=1'b1 ; C=1'b1;

end


initial
begin
$monitor($time, "A2=%b, B2=%b, C2=%b,Y=%b", A,B,C,Y);
end
initial
begin
$dumpfile ("circuit2.vcd");
 $dumpvars (0, tb_simple_circuit);
end
endmodule

Lab-2/circuit1.vcd
$date
	Tue Aug 16 12:49:28 2022
$end
$version
	Icarus Verilog
$end
$timescale
	1s
$end
$scope module tb_simple_circuit $end
$var wire 1 ! Y $end
$var reg 1 " A $end
$var reg 1 # B $end
$var reg 1 $ C $end
$scope module M1 $end
$var wire 1 % A $end
$var wire 1 & B $end
$var wire 1 ' C $end
$var wire 1 ! Y $end
$var wire 1 ( w1 $end
$upscope $end
$upscope $end
$enddefinitions $end
#0
$dumpvars
0(
0'
0&
0%
0$
0#
0"
0!
$end
#20
1$
1'
#40
0$
0'
1#
1&
#60
1!
1(
1$
1'
#80
0(
0$
0'
0#
0&
1"
1%
#100
1$
1'
#120
0$
0'
1#
1&
#140
1(
1$
1'
