Lab-2/circuit3.v
module simple_circuit
(A, B, C, D, E);
output D, E;
input A, B, C;
wire w1;
and G1 (w1,A,B);
not G2 (E,C);
or G3 (D,E,w1);
endmodule

Lab-2/circuit3_tb.v
module tb_simple_circuit;

reg A,B,C;
wire Y, Z;

simple_circuit M1(.D(Y), .E(Z), .A(A), .B(B), .C(C));

initial

begin

A=1'b0 ; B=1'b0 ; C=1'b0;
#20
A=1'b0 ; B=1'b0 ; C=1'b1;
#20
A=1'b0 ; B=1'b1 ; C=1'b0;
#20
A=1'b0 ; B=1'b1 ; C=1'b1;
#20
A=1'b1 ; B=1'b0 ; C=1'b0;
#20
A=1'b1 ; B=1'b0 ; C=1'b1;
#20
A=1'b1 ; B=1'b1 ; C=1'b0;
#20
A=1'b1 ; B=1'b1 ; C=1'b1;

end


initial
begin
$monitor($time, "A2=%b, B2=%b, C2=%b,Y=%b, Z=%b", A,B,C,Y, Z);
end
initial
begin
$dumpfile ("circuit3.vcd");
 $dumpvars (0, tb_simple_circuit);
end
endmodule

Lab-2/circuit.vcd
$date
	Tue Aug 23 12:26:41 2022
$end
$version
	Icarus Verilog
$end
$timescale
	1s
$end
$scope module tb_simple_circuit $end
$var wire 1 ! Y $end
$var wire 1 " Z $end
$var reg 1 # A $end
$var reg 1 $ B $end
$var reg 1 % C $end
$scope module M1 $end
$var wire 1 & A $end
$var wire 1 ' B $end
$var wire 1 ( C $end
$var wire 1 ! D $end
$var wire 1 " E $end
$var wire 1 ) w1 $end
$upscope $end
$upscope $end
$enddefinitions $end
#0
$dumpvars
0)
0(
0'
0&
0%
0$
0#
1"
1!
$end
#20
0!
0"
1%
1(
#40
1!
1"
0%
0(
1$
1'
#60
0!
0"
1%
1(
#80
1!
1"
0%
0(
0$
0'
1#
1&
#100
0!
0"
1%
1(
#120
1!
1"
1)
0%
0(
1$
1'
#140
0"
1%
1(
