Lab-3/full_add.v
module fulladd(a, b, cin, sum, cout);
input a, b, cin;
output sum, cout;
wire w1, w2, w3, w4, w5;

xor g1(w1, a, b);
xor g2(sum, w1, cin);

and g3(w2, a, b);
and g4(w3, b, cin);
and g5(w4, cin, a);

or g6(w5, w4, w3);
or g7(cout, w5, w2);

endmodule

Lab-3/fulladd_tb.v
module fulladd_tb;

reg aa,bb,cc;

wire ss,cy;

fulladd add1(.a(aa), .b(bb), .cin(cc), .sum(ss), .cout(cy));

initial

begin

$dumpfile("full_add_test.vcd");

$dumpvars(0, fulladd_tb);

end


initial
 begin 
$monitor($time, "a=%b, b=%b, c=%b,sum=%b,carry=%b", aa,bb,cc,ss,cy);
aa = 1'b0;
bb = 1'b0;
cc=1'b0;

#5
  aa = 1'b0;
bb = 1'b0;
cc=1'b1;

#5
  aa = 1'b0;
bb = 1'b1;
cc=1'b0;

#5
  aa = 1'b0;
bb = 1'b1;
cc=1'b1;

#5
  aa = 1'b1;
bb = 1'b0;
cc=1'b0;

#5
  aa = 1'b1;
bb = 1'b0;
cc=1'b1;

#5
  aa = 1'b1;
bb = 1'b1;
cc=1'b0;

#5
  aa = 1'b1;
bb = 1'b1;
cc=1'b1;

end

endmodule

Lab-3/full_add_test.vcd
$date
	Tue Aug 23 14:17:24 2022
$end
$version
	Icarus Verilog
$end
$timescale
	1s
$end
$scope module fulladd_tb $end
$var wire 1 ! cy $end
$var wire 1 " ss $end
$var reg 1 # aa $end
$var reg 1 $ bb $end
$var reg 1 % cc $end
$scope module add1 $end
$var wire 1 & a $end
$var wire 1 ' b $end
$var wire 1 ( cin $end
$var wire 1 ! cout $end
$var wire 1 " sum $end
$var wire 1 ) w1 $end
$var wire 1 * w2 $end
$var wire 1 + w3 $end
$var wire 1 , w4 $end
$var wire 1 - w5 $end
$upscope $end
$upscope $end
$enddefinitions $end
#0
$dumpvars
0-
0,
0+
0*
0)
0(
0'
0&
0%
0$
0#
0"
0!
$end
#5
1"
1%
1(
#10
1)
0%
0(
1$
1'
#15
1!
1-
0"
1+
1%
1(
#20
0!
0-
1"
0+
0%
0(
0$
0'
1#
1&
#25
1!
1-
0"
1,
1%
1(
#30
0-
0,
0)
1*
0%
0(
1$
1'
#35
1-
1"
1+
1,
1%
1(
